Workbook

Sheet Master Data
A1: TECHNOLOGY - SEMICONDUCTOR INDUSTRY
A3: Total Revenue
A4: Companies (in USD millions) | B4: 2024 | C4: 2023 | D4: 2022 | E4: 2021 | F4: 2020 | G4: AVG | H4: RANK
A5: NVIDIA | B5: =NVIDIA!B6 -> 60922 | C5: =NVIDIA!C6 -> 26974 | D5: =NVIDIA!D6 -> 26914 | E5: =NVIDIA!E6 -> 16675 | F5: =NVIDIA!F6 -> 10918 | G5: =AVERAGE(Table6[[#This Row],[2024]:[2020]]) -> 28480.6 | H5: 4
A6: AMD | B6: =AMD!B6 -> 25785 | C6: =AMD!C6 -> 22680 | D6: =AMD!D6 -> 23601 | E6: =AMD!E6 -> 16434 | F6: =AMD!F6 -> 9763 | G6: =AVERAGE(Table6[[#This Row],[2024]:[2020]]) -> 19652.6 | H6: 5
A7: Qualcomm | B7: =Qualcomm!B5 -> 38962 | C7: =Qualcomm!C5 -> 35820 | D7: =Qualcomm!D5 -> 44200 | E7: =Qualcomm!E5 -> 33566 | F7: =Qualcomm!F5 -> 23531 | G7: =AVERAGE(Table6[[#This Row],[2024]:[2020]]) -> 35215.8 | H7: 3
A8: ARM | B8: =ARM!B7 -> 4007 | C8: =ARM!C7 -> 3233 | D8: =ARM!D7 -> 2679 | E8: =ARM!E7 -> 2703 | F8: =ARM!F7 -> 2027 | G8: =AVERAGE(Table6[[#This Row],[2024]:[2020]]) -> 2929.8 | H8: 6
A9: TSMC | B9: =TSMC!B4*32.108 -> 92930.184 | C9: =TSMC!C4*31.15 -> 67336.955 | D9: =TSMC!D4*29.777 -> 67412.15 | E9: =TSMC!E4*28.022 -> 44482.123 | F9: =TSMC!F4*29.578 -> 39613.815 | G9: =AVERAGE(Table6[[#This Row],[2024]:[2020]]) -> 62355.046 | H9: 2
A10: Intel | B10: =Intel!B5 -> 53101 | C10: =Intel!C5 -> 54228 | D10: =Intel!D5 -> 63054 | E10: =Intel!E5 -> 79024 | F10: =Intel!F5 -> 77867 | G10: =AVERAGE(Table6[[#This Row],[2024]:[2020]]) -> 65454.8 | H10: 1
A12: Revenue YoY Growth (%)
A13: Companies | B13: 2024/23 | C13: 2023/22 | D13: 2022/21 | E13: 2021/20 | F13: CAGR | G13: RANK
A14: NVIDIA | B14: =B5/C5-1 -> 1.2585453 | C14: =C5/D5-1 -> 0.002229323 | D14: =D5/E5-1 -> 0.61403298 | E14: =E5/F5-1 -> 0.52729438 | F14: =(B5 / F5)^(1/4) - 1 -> 0.53694302 | G14: =RANK(F14,F14:F19,0) -> 1
A15: AMD | B15: =B6/C6-1 -> 0.13690476 | C15: =C6/D6-1 -> -0.03902377 | D15: =D6/E6-1 -> 0.43610807 | E15: =E6/F6-1 -> 0.68329407 | F15: =(B6 / F6)^(1/4) - 1 -> 0.27481147 | G15: =RANK(F15,F14:F19,0) -> 2
A16: Qualcomm | B16: =B7/C7-1 -> 0.08771636 | C16: =C7/D7-1 -> -0.18959276 | D16: =D7/E7-1 -> 0.31680868 | E16: =E7/F7-1 -> 0.42645871 | F16: =(B7 / F7)^(1/4) - 1 -> 0.1343582 | G16: 3
A17: ARM | B17: =B8/C8-1 -> 0.23940612 | C17: =C8/D8-1 -> 0.20679358 | D17: =D8/E8-1 -> -0.0088790233 | E17: =E8/F8-1 -> 0.33349778 | F17: =(B8 / F8)^(1/4) - 1 -> 0.18574526 | G17: 4
A18: TSMC | B18: =B9/C9-1 -> 0.38007702 | C18: =C9/D9-1 -> -0.0011154562 | D18: =D9/E9-1 -> 0.51548861 | E18: =E9/F9-1 -> 0.12289418 | F18: =(B9 / F9)^(1/4) - 1 -> 0.23759211 | G18: 5
A19: Intel | B19: =B10/C10-1 -> -0.020782622 | C19: =C10/D10-1 -> -0.13997526 | D19: =D10/E10-1 -> -0.2020905 | E19: =E10/F10-1 -> 0.014858669 | F19: =(B10 / F10)^(1/4) - 1 -> -0.091264877 | G19: 6
A21: Total Cost of Sales
A22: Companies | B22: 2024 | C22: 2023 | D22: 2022 | E22: 2021 | F22: 2020 | G22: AVG | H22: RANK
A23: NVIDIA | B23: =NVIDIA!B7 -> 16621 | C23: =NVIDIA!C7 -> 11618 | D23: =NVIDIA!D7 -> 9439 | E23: =NVIDIA!E7 -> 6279 | F23: =NVIDIA!F7 -> 4150 | G23: =AVERAGE(B23:F23) -> 9621.4 | H23: =_xlfn.RANK.EQ(G23,G23:G28,1) -> 3
A24: AMD | B24: =AMD!B7 -> 13060 | C24: =AMD!C7 -> 12220 | D24: =AMD!D7 -> 12998 | E24: =AMD!E7 -> 8505 | F24: =AMD!F7 -> 5416 | G24: =AVERAGE(B24:F24) -> 10439.8 | H24: =_xlfn.RANK.EQ(G24,G23:G28,1) -> 4
A25: Qualcomm | B25: =Qualcomm!B6 -> 17060 | C25: =Qualcomm!C6 -> 15869 | D25: =Qualcomm!D6 -> 18635 | E25: =Qualcomm!E6 -> 14262 | F25: =Qualcomm!F6 -> 9255 | G25: =AVERAGE(B25:F25) -> 15016.2 | H25: =_xlfn.RANK.EQ(G25,G23:G28,1) -> 5
A26: ARM | B26: =ARM!B9 -> -121 | C26: =ARM!C9 -> -154 | D26: =ARM!D9 -> -106 | E26: =ARM!E9 -> -131 | F26: =ARM!F9 -> -145 | G26: =AVERAGE(B26:F26) -> -131.4 | H26: =_xlfn.RANK.EQ(G26,G23:G28,1) -> 1
A27: TSMC | B27: =TSMC!B5*32.108 -> 40777.16 | C27: =TSMC!C5*31.15 -> 30732.59 | D27: =TSMC!D5*29.777 -> 27260.844 | E27: =TSMC!E5*28.022 -> 21518.094 | F27: =TSMC!F5*29.578 -> 18577.942 | G27: =AVERAGE(B27:F27) -> 27773.326 | H27: =_xlfn.RANK.EQ(G27,G23:G28,1) -> 6
A28: Intel | B28: =Intel!B6 -> 34877 | C28: =Intel!C6 -> 31282 | D28: =Intel!D6 -> 34608 | E28: =Intel!E6 -> 35209 | F28: =Intel!F6 -> 34255 | G28: =Intel!G6 -> 0 | H28: =_xlfn.RANK.EQ(G28,G23:G28,1) -> 2
A30: Cost of Sales to Total Sales
A31: Companies | B31: 2024 | C31: 2023 | D31: 2022 | E31: 2021 | F31: 2020 | G31: AVG | H31: RANK
A32: NVIDIA | B32: =B23/B5 -> 0.27282427 | C32: =C23/C5 -> 0.43071106 | D32: =D23/D5 -> 0.35070967 | E32: =E23/E5 -> 0.37655172 | F32: =F23/F5 -> 0.38010625 | G32: =AVERAGE(B32:F32) -> 0.36218059 | H32: =_xlfn.RANK.EQ(G32,G32:G37,1) -> 2
A33: AMD | B33: =B24/B6 -> 0.50649602 | C33: =C24/C6 -> 0.53880071 | D33: =D24/D6 -> 0.55073938 | E33: =E24/E6 -> 0.51752464 | F33: =F24/F6 -> 0.55474752 | G33: =AVERAGE(B33:F33) -> 0.53366165 | H33: =_xlfn.RANK.EQ(G33,G32:G37,1) -> 6
A34: Qualcomm | B34: =B25/B7 -> 0.43786253 | C34: =C25/C7 -> 0.44302066 | D34: =D25/D7 -> 0.42160633 | E34: =E25/E7 -> 0.42489424 | F34: =F25/F7 -> 0.39331095 | G34: =AVERAGE(B34:F34) -> 0.42413894 | H34: =_xlfn.RANK.EQ(G34,G32:G37,1) -> 3
A35: ARM | B35: =B26/B8 -> -0.030197155 | C35: =C26/C8 -> -0.047633777 | D35: =D26/D8 -> -0.039567003 | E35: =E26/E8 -> -0.048464669 | F35: =F26/F8 -> -0.071534287 | G35: =AVERAGE(B35:F35) -> -0.047479378 | H35: =_xlfn.RANK.EQ(G35,G32:G37,1) -> 1
A36: TSMC | B36: =B27/B9 -> 0.43879349 | C36: =C27/C9 -> 0.45640006 | D36: =D27/D9 -> 0.40439065 | E36: =E27/E9 -> 0.48374701 | F36: =F27/F9 -> 0.46897633 | G36: =AVERAGE(B36:F36) -> 0.45046151 | H36: =_xlfn.RANK.EQ(G36,G32:G37,1) -> 4
A37: Intel | B37: =B28/B10 -> 0.65680496 | C37: =C28/C10 -> 0.57686066 | D37: =D28/D10 -> 0.54886288 | E37: =E28/E10 -> 0.44554819 | F37: =F28/F10 -> 0.43991678 | G37: =AVERAGE(B37:F37) -> 0.53359869 | H37: =_xlfn.RANK.EQ(G37,G32:G37,1) -> 5
A39: Operating Expenses to Total Sales
A40: Companies | B40: 2024 | C40: 2023 | D40: 2022 | E40: 2021 | F40: 2020 | G40: AVG | H40: RANK
A41: NVIDIA | B41: =B168/B5 -> 0.1859591 | C41: =C168/C5 -> 0.41269371 | D41: =D168/D5 -> 0.27621312 | E41: =E168/E5 -> 0.35166417 | F41: =F168/F5 -> 0.3592233 | G41: =AVERAGE(B41:F41) -> 0.31715068 | H41: =_xlfn.RANK.EQ(G41,G41:G46,1) -> 2
A42: AMD | B42: =B169/B6 -> 0.41981772 | C42: =C169/C6 -> 0.23536155 | D42: =D169/D6 -> 0.39570357 | E42: =E169/E6 -> 0.26049653 | F42: =F169/F6 -> 0.30502919 | G42: =AVERAGE(B42:F42) -> 0.32328171 | H42: =_xlfn.RANK.EQ(G42,G41:G46,1) -> 3
A43: Qualcomm | B43: =B170/B7 -> 0.34284688 | C43: =C170/C7 -> 0.36599665 | D43: =D170/D7 -> 0.28339367 | E43: =E170/E7 -> 0.3306024 | F43: =F170/F7 -> 0.40125792 | G43: =AVERAGE(B43:F43) -> 0.3448195 | H43: =_xlfn.RANK.EQ(G43,G41:G46,1) -> 4
A44: ARM | B44: =B171/B8 -> 0.76241577 | C44: =C171/C8 -> 0.91803279 | D44: =D171/D8 -> 0.70996641 | E44: =E171/E8 -> 0.71735109 | F44: =F171/F8 -> 0.81055747 | G44: =AVERAGE(B44:F44) -> 0.78366471 | H44: =_xlfn.RANK.EQ(G44,G41:G46,1) -> 6
A45: TSMC | B45: =B172/B9 -> 0.0027181696 | C45: =C172/C9 -> 0.0033651655 | D45: =D172/D9 -> 0.0030409948 | E45: =E172/E9 -> 0.0033384198 | F45: =F172/F9 -> 0.0031630379 | G45: =AVERAGE(B45:F45) -> 0.0031251575 | H45: =_xlfn.RANK.EQ(G45,G41:G46,1) -> 1
A46: Intel | B46: =B173/B10 -> 0.41530291 | C46: =C173/C10 -> 0.39979346 | D46: =D173/D10 -> 0.38903162 | E46: =E173/E10 -> 0.27501772 | F46: =F173/F10 -> 0.25345782 | G46: =AVERAGE(B46:F46) -> 0.34652071 | H46: =_xlfn.RANK.EQ(G46,G41:G46,1) -> 5
A48: OpEx YoY Growth (%)
A49: Companies | B49: 2024/23 | C49: 2023/22 | D49: 2022/21 | E49: 2021/20 | F49: AVG | G49: RANK
A50: NVIDIA | B50: =B168/C168-1 -> 0.01769673 | C50: =C168/D168-1 -> 0.49744418 | D50: =D168/E168-1 -> 0.26773533 | E50: =E168/F168-1 -> 0.49515553 | F50: =AVERAGE(B50:E50) -> 0.31950794 | G50: =_xlfn.RANK.EQ(F50,F50:F55,0) -> 2
A51: AMD | B51: =B169/C169-1 -> 1.0279131 | C51: =C169/D169-1 -> -0.42841846 | D51: =D169/E169-1 -> 1.1814996 | E51: =E169/F169-1 -> 0.43754197 | F51: =AVERAGE(B51:E51) -> 0.55463406 | G51: =_xlfn.RANK.EQ(F51,F50:F55,0) -> 1
A52: Qualcomm | B52: =B170/C170-1 -> 0.018916857 | C52: =C170/D170-1 -> 0.046623024 | D52: =D170/E170-1 -> 0.12877354 | E52: =E170/F170-1 -> 0.17528066 | F52: =AVERAGE(B52:E52) -> 0.092398521 | G52: =_xlfn.RANK.EQ(F52,F50:F55,0) -> 5
A53: ARM | B53: =B171/C171-1 -> 0.029312668 | C53: =C171/D171-1 -> 0.56046267 | D53: =D171/E171-1 -> -0.019082001 | E53: =E171/F171-1 -> 0.18015825 | F53: =AVERAGE(B53:E53) -> 0.1877129 | G53: =_xlfn.RANK.EQ(F53,F50:F55,0) -> 4
A54: TSMC | B54: =B172/C172-1 -> 0.11473963 | C54: =C172/D172-1 -> 0.10536585 | D54: =D172/E172-1 -> 0.38047138 | E54: =E172/F172-1 -> 0.18515563 | F54: =AVERAGE(B54:E54) -> 0.19643312 | G54: =_xlfn.RANK.EQ(F54,F50:F55,0) -> 3
A55: Intel | B55: =B173/C173-1 -> 0.017204797 | C55: =C173/D173-1 -> -0.11618426 | D55: =D173/E173-1 -> 0.12869829 | E55: =E173/F173-1 -> 0.10118565 | F55: =AVERAGE(B55:E55) -> 0.032726119 | G55: =_xlfn.RANK.EQ(F55,F50:F55,0) -> 6
A57: Research and Development (R&D) Expenses to Total Sales
A58: Companies | B58: 2024 | C58: 2023 | D58: 2022 | E58: 2021 | F58: 2020 | G58: AVG | H58: RANK
A59: NVIDIA | B59: =NVIDIA!B44/NVIDIA!B6 -> 0.14239519 | C59: =NVIDIA!C44/NVIDIA!C6 -> 0.27207681 | D59: =NVIDIA!D44/NVIDIA!D6 -> 0.19573456 | E59: =NVIDIA!E44/NVIDIA!E6 -> 0.23532234 | F59: =NVIDIA!F44/NVIDIA!F6 -> 0.25911339 | G59: =AVERAGE(B59:F59) -> 0.22092846 | H59: =_xlfn.RANK.EQ(G59,G59:G64,0) -> 4
A60: AMD | B60: =AMD!B36/AMD!B6 -> 0.25037813 | C60: =AMD!C36/AMD!C6 -> 0.25890653 | D60: =AMD!D36/AMD!D6 -> 0.21206729 | E60: =AMD!E36/AMD!E6 -> 0.17311671 | F60: =AMD!F36/AMD!F6 -> 0.2031138 | G60: =AVERAGE(B60:F60) -> 0.21951649 | H60: =_xlfn.RANK.EQ(G60,G59:G64,0) -> 5
A61: Qualcomm | B61: =Qualcomm!B31/Qualcomm!B5 -> 0.22824804 | C61: =Qualcomm!C31/Qualcomm!C5 -> 0.24617532 | D61: =Qualcomm!D31/Qualcomm!D5 -> 0.18538462 | E61: =Qualcomm!E31/Qualcomm!E5 -> 0.21378776 | F61: =Qualcomm!F31/Qualcomm!F5 -> 0.25392036 | G61: =AVERAGE(B61:F61) -> 0.22550322 | H61: =_xlfn.RANK.EQ(G61,G59:G64,0) -> 3
A62: ARM | B62: =ARM!B32/ARM!B7 -> 0.51684552 | C62: =ARM!C32/ARM!C7 -> 0.61212496 | D62: =ARM!D32/ARM!D7 -> 0.422919 | E62: =ARM!E32/ARM!E7 -> 0.36810951 | F62: =ARM!F32/ARM!F7 -> 0.40157869 | G62: =AVERAGE(B62:F62) -> 0.46431554 | H62: =_xlfn.RANK.EQ(G62,G59:G64,0) -> 1
A63: TSMC | B63: =TSMC!B28/TSMC!B4 -> 0.06872128 | C63: =TSMC!C28/TSMC!C4 -> 0.083082759 | D63: =TSMC!D28/TSMC!D4 -> 0.072397191 | E63: =TSMC!E28/TSMC!E4 -> 0.072760489 | F63: =TSMC!F28/TSMC!F4 -> 0.07250056 | G63: =AVERAGE(B63:F63) -> 0.073892456 | H63: =_xlfn.RANK.EQ(G63,G59:G64,0) -> 6
A64: Intel | B64: =Intel!B32/Intel!B5 -> 0.31159489 | C64: =Intel!C32/Intel!C5 -> 0.2958988 | D64: =Intel!D32/Intel!D5 -> 0.27798395 | E64: =Intel!E32/Intel!E5 -> 0.19222009 | F64: =Intel!F32/Intel!F5 -> 0.17409172 | G64: =AVERAGE(B64:F64) -> 0.25035789 | H64: =_xlfn.RANK.EQ(G64,G59:G64,0) -> 2
A66: Operating Profit Margin (%)
A67: Companies | B67: 2024 | C67: 2023 | D67: 2022 | E67: 2021 | F67: 2020 | G67: AVG | H67: RANK
A68: NVIDIA | B68: =NVIDIA!B10/NVIDIA!B6 -> 0.54121664 | C68: =NVIDIA!C10/NVIDIA!C6 -> 0.15659524 | D68: =NVIDIA!D10/NVIDIA!D6 -> 0.37307721 | E68: =NVIDIA!E10/NVIDIA!E6 -> 0.27178411 | F68: =NVIDIA!F10/NVIDIA!F6 -> 0.26067045 | G68: =AVERAGE(B68:F68) -> 0.32066873 | H68: =_xlfn.RANK.EQ(G68,G68:G73,0) -> 2
A69: AMD | B69: =AMD!B10/AMD!B6 -> 0.073686252 | C69: =AMD!C10/AMD!C6 -> 0.017680776 | D69: =AMD!D10/AMD!D6 -> 0.053557053 | E69: =AMD!E10/AMD!E6 -> 0.22197882 | F69: =AMD!F10/AMD!F6 -> 0.14022329 | G69: =AVERAGE(B69:F69) -> 0.10142524 | H69: =_xlfn.RANK.EQ(G69,G68:G73,0) -> 6
A70: Qualcomm | B70: =Qualcomm!B9/Qualcomm!B5 -> 0.21929059 | C70: =Qualcomm!C9/Qualcomm!C5 -> 0.19098269 | D70: =Qualcomm!D9/Qualcomm!D5 -> 0.295 | E70: =Qualcomm!E9/Qualcomm!E5 -> 0.24450337 | F70: =Qualcomm!F9/Qualcomm!F5 -> 0.20543113 | G70: =AVERAGE(B70:F70) -> 0.23104156 | H70: =_xlfn.RANK.EQ(G70,G68:G73,0) -> 3
A71: ARM | B71: =ARM!B12/ARM!B7 -> 0.20738707 | C71: =ARM!C12/ARM!C7 -> 0.034333436 | D71: =ARM!D12/ARM!D7 -> 0.25046659 | E71: =ARM!E12/ARM!E7 -> 0.23418424 | F71: =ARM!F12/ARM!F7 -> 0.11790824 | G71: =AVERAGE(B71:F71) -> 0.16885592 | H71: =_xlfn.RANK.EQ(G71,G68:G73,0) -> 4
A72: TSMC | B72: =TSMC!B7/TSMC!B4 -> 0.45679439 | C72: =TSMC!C7/TSMC!C4 -> 0.42628487 | D72: =TSMC!D7/TSMC!D4 -> 0.49529573 | E72: =TSMC!E7/TSMC!E4 -> 0.40947461 | F72: =TSMC!F7/TSMC!F4 -> 0.42320615 | G72: =AVERAGE(B72:F72) -> 0.44221115 | H72: =_xlfn.RANK.EQ(G72,G68:G73,0) -> 1
A73: Intel | B73: =Intel!B10/Intel!B5 -> -0.07210787 | C73: =Intel!C10/Intel!C5 -> 0.023345873 | D73: =Intel!D10/Intel!D5 -> 0.062105497 | E73: =Intel!E10/Intel!E5 -> 0.2794341 | F73: =Intel!F10/Intel!F5 -> 0.3066254 | G73: =AVERAGE(B73:F73) -> 0.1198806 | H73: =_xlfn.RANK.EQ(G73,G68:G73,0) -> 5
A75: YoY Operating Profit Margin Growth (%) | J75: Segmented Revenue Growth (%) | P75: YoY Segmented Revenue Growth (%)
A76: Companies | B76: 2024/23 | C76: 2023/22 | D76: 2022/21 | E76: 2021/20 | F76: AVG | G76: RANK | J76: Data Center/AI | P76: Data Center/AI
A77: NVIDIA | B77: =B68/C68-1 -> 2.45615 | C77: =C68/D68-1 -> -0.5802605 | D77: =D68/E68-1 -> 0.37269692 | E77: =E68/F68-1 -> 0.042634888 | F77: =AVERAGE(B77:E77) -> 0.57280533 | G77: =_xlfn.RANK.EQ(F77,F77:F82,0) -> 3 | J77: Companies | K77: 2024 | L77: 2023 | M77: 2022 | N77: 2021 | O77: 2020 | P77: Companies | Q77: 2024/23 | R77: 2023/22 | S77: 2022/21 | T77: 2021/20
A78: AMD | B78: =B69/C69 -> 4.1675915 | C78: =C69/D69 -> 0.33012974 | D78: =D69/E69 -> 0.241271 | E78: =E69/F69 -> 1.5830382 | F78: =AVERAGE(B78:E78) -> 1.5805076 | G78: =_xlfn.RANK.EQ(F78,F77:F82,0) -> 1 | J78: NVIDIA | K78: =NVIDIA!B52/NVIDIA!B57 -> 0.78009586 | L78: =NVIDIA!C52/NVIDIA!C57 -> 0.55627641 | M78: =NVIDIA!D52/NVIDIA!D57 -> 0.39433009 | N78: =NVIDIA!E52/NVIDIA!E57 -> 0.40155922 | O78: =NVIDIA!F52/NVIDIA!F57 -> 0.27321854 | P78: NVIDIA | Q78: =K78/L78-1 -> 0.40235293 | R78: =L78/M78-1 -> 0.41068722 | S78: =M78/N78-1 -> -0.018002655 | T78: =N78/O78-1 -> 0.46973636
A79: Qualcomm | B79: =B70/C70-1 -> 0.14822233 | C79: =C70/D70-1 -> -0.35260105 | D79: =D70/E70-1 -> 0.20652735 | E79: =E70/F70-1 -> 0.19019626 | F79: =AVERAGE(B79:E79) -> 0.048086224 | G79: =_xlfn.RANK.EQ(F79,F77:F82,0) -> 4 | J79: AMD | K79: =AMD!B45/AMD!B49 -> 0.48784177 | L79: =AMD!C45/AMD!C49 -> 0.28641975 | M79: =AMD!D45/AMD!D49 -> 0.25604847 | N79: =AMD!E45/AMD!E49 -> 0.2247779 | O79: =AMD!F45/AMD!F49 -> 0.17259039 | P79: AMD | Q79: =K79/L79-1 -> 0.70324066 | R79: =L79/M79-1 -> 0.11861536 | S79: =M79/N79-1 -> 0.13911765 | T79: =N79/O79-1 -> 0.30237782
A80: ARM | B80: =B71/C71-1 -> 5.040382 | C80: =C71/D71-1 -> -0.86292209 | D80: =D71/E71-1 -> 0.069527959 | E80: =E71/F71-1 -> 0.98615671 | F80: =AVERAGE(B80:E80) -> 1.3082862 | G80: =_xlfn.RANK.EQ(F80,F77:F82,0) -> 2 | J80: Qualcomm | K80: NA | L80: NA | M80: NA | N80: NA | O80: NA | P80: Qualcomm | Q80: NA | R80: NA | S80: NA | T80: NA
A81: TSMC | B81: =B72/C72-1 -> 0.071570733 | C81: =C72/D72-1 -> -0.13933264 | D81: =D72/E72-1 -> 0.20958837 | E81: =E72/F72-1 -> -0.032446456 | F81: =AVERAGE(B81:E81) -> 0.027345002 | G81: =_xlfn.RANK.EQ(F81,F77:F82,0) -> 5 | J81: Intel | K81: =Intel!B55/Intel!B60 -> 0.24137022 | L81: =Intel!C55/Intel!C60 -> 0.28621745 | M81: =Intel!D55/Intel!D60 -> 0.30838646 | N81: =Intel!E55/Intel!E60 -> 0.28819093 | O81: =Intel!F55/Intel!F60 -> 0.29823958 | P81: Intel | Q81: =K81/L81-1 -> -0.15668937 | R81: =L81/M81-1 -> -0.071887106 | S81: =M81/N81-1 -> 0.070076921 | T81: =N81/O81-1 -> -0.033693217
A82: Intel | B82: =B73/C73-1 -> -4.0886774 | C82: =C73/D73-1 -> -0.62409329 | D82: =D73/E73-1 -> -0.77774546 | E82: =E73/F73-1 -> -0.088679228 | F82: =AVERAGE(B82:E82) -> -1.3947988 | G82: =_xlfn.RANK.EQ(F82,F77:F82,0) -> 6 | J82: Gaming/Graphics | P82: Gaming/Graphics
J83: Companies | K83: 2024 | L83: 2023 | M83: 2022 | N83: 2021 | O83: 2020 | P83: Companies | Q83: 2024/23 | R83: 2023/22 | S83: 2022/21 | T83: 2021/20
A84: Gross Profit Margin (%) | J84: NVIDIA | K84: =NVIDIA!B53/NVIDIA!B57 -> 0.17148157 | L84: =NVIDIA!C53/NVIDIA!C57 -> 0.3361385 | M84: =NVIDIA!D53/NVIDIA!D57 -> 0.46303039 | N84: =NVIDIA!E53/NVIDIA!E57 -> 0.46530735 | O84: =NVIDIA!F53/NVIDIA!F57 -> 0.50540392 | P84: NVIDIA | Q84: =K84/L84-1 -> -0.48984849 | R84: =L84/M84-1 -> -0.27404657 | S84: =M84/N84-1 -> -0.0048934392 | T84: =N84/O84-1 -> -0.0793357
A85: Companies | B85: 2024 | C85: 2023 | D85: 2022 | E85: 2021 | F85: 2020 | G85: AVG | H85: RANK | J85: AMD | K85: =AMD!B47/AMD!B49 -> 0.10063991 | L85: =AMD!C47/AMD!C49 -> 0.27389771 | M85: =AMD!D47/AMD!D49 -> 0.28833524 | N85: =AMD!E47/AMD!E49 -> 0.34118291 | O85: =AMD!F47/AMD!F49 -> 0.281266 | P85: AMD | Q85: =K85/L85-1 -> -0.63256389 | R85: =L85/M85-1 -> -0.050072037 | S85: =M85/N85-1 -> -0.15489543 | T85: =N85/O85-1 -> 0.21302578
A86: NVIDIA | B86: =NVIDIA!B8/NVIDIA!B6 -> 0.72717573 | C86: =NVIDIA!C8/NVIDIA!C6 -> 0.56928894 | D86: =NVIDIA!D8/NVIDIA!D6 -> 0.64929033 | E86: =NVIDIA!E8/NVIDIA!E6 -> 0.62344828 | F86: =NVIDIA!F8/NVIDIA!F6 -> 0.61989375 | G86: =AVERAGE(B86:F86) -> 0.63781941 | H86: =_xlfn.RANK.EQ(G86,G86:G91,0) -> 2 | J86: Qualcomm | K86: NA | L86: NA | M86: NA | N86: NA | O86: NA | P86: Qualcomm | Q86: NA | R86: NA | S86: NA | T86: NA
A87: AMD | B87: =AMD!B8/AMD!B6 -> 0.49350398 | C87: =AMD!C8/AMD!C6 -> 0.46119929 | D87: =AMD!D8/AMD!D6 -> 0.44926062 | E87: =AMD!E8/AMD!E6 -> 0.48247536 | F87: =AMD!F8/AMD!F6 -> 0.44525248 | G87: =AVERAGE(B87:F87) -> 0.46633835 | H87: =_xlfn.RANK.EQ(G87,G86:G91,0) -> 6 | J87: Intel | K87: NA | L87: NA | M87: NA | N87: NA | O87: NA | P87: Intel | Q87: NA | R87: NA | S87: NA | T87: NA
A88: Qualcomm | B88: =Qualcomm!B7/Qualcomm!B5 -> 0.56213747 | C88: =Qualcomm!C7/Qualcomm!C5 -> 0.55697934 | D88: =Qualcomm!D7/Qualcomm!D5 -> 0.57839367 | E88: =Qualcomm!E7/Qualcomm!E5 -> 0.57510576 | F88: =Qualcomm!F7/Qualcomm!F5 -> 0.60668905 | G88: =AVERAGE(B88:F88) -> 0.57586106 | H88: =_xlfn.RANK.EQ(G88,G86:G91,0) -> 3 | J88: Consumer | P88: Consumer
A89: ARM | B89: =ARM!B10/ARM!B7 -> 0.96980285 | C89: =ARM!C10/ARM!C7 -> 0.95236622 | D89: =ARM!D10/ARM!D7 -> 1.0350877 | E89: =ARM!E10/ARM!E7 -> 1.0484647 | F89: =ARM!F10/ARM!F7 -> 0.92846571 | G89: =AVERAGE(B89:F89) -> 0.98683743 | H89: =_xlfn.RANK.EQ(G89,G86:G91,0) -> 1 | J89: Companies | K89: 2024 | L89: 2023 | M89: 2022 | N89: 2021 | O89: 2020 | P89: Companies | Q89: 2024/23 | R89: 2023/22 | S89: 2022/21 | T89: 2021/20
A90: TSMC | B90: =TSMC!B6/TSMC!B4 -> 0.56120651 | C90: =TSMC!C6/TSMC!C4 -> 0.54359994 | D90: =TSMC!D6/TSMC!D4 -> 0.59560935 | E90: =TSMC!E6/TSMC!E4 -> 0.51625299 | F90: =TSMC!F6/TSMC!F4 -> 0.530949 | G90: =AVERAGE(B90:F90) -> 0.54952356 | H90: =_xlfn.RANK.EQ(G90,G86:G91,0) -> 4 | J90: NVIDIA | K90: =NVIDIA!B56/NVIDIA!B57 -> 0.0050228161 | L90: =NVIDIA!C56/NVIDIA!C57 -> 0.016868095 | M90: =NVIDIA!D56/NVIDIA!D57 -> 0.043174556 | N90: =NVIDIA!E56/NVIDIA!E57 -> 0.037841079 | O90: =NVIDIA!F56/NVIDIA!F57 -> 0.046253893 | P90: NVIDIA | Q90: =K90/L90-1 -> -0.7022298 | R90: =L90/M90-1 -> -0.60930472 | S90: =M90/N90-1 -> 0.14094409 | T90: =N90/O90-1 -> -0.18188336
A91: Intel | B91: =Intel!B7/Intel!B5 -> 0.34319504 | C91: =Intel!C7/Intel!C5 -> 0.42313934 | D91: =Intel!D7/Intel!D5 -> 0.45113712 | E91: =Intel!E7/Intel!E5 -> 0.55445181 | F91: =Intel!F7/Intel!F5 -> 0.56008322 | G91: =AVERAGE(B91:F91) -> 0.46640131 | H91: =_xlfn.RANK.EQ(G91,G86:G91,0) -> 5 | J91: AMD | K91: =AMD!B46/AMD!B49 -> 0.2735699 | L91: =AMD!C46/AMD!C49 -> 0.20507055 | M91: =AMD!D46/AMD!D49 -> 0.2627431 | N91: =AMD!E46/AMD!E49 -> 0.41907022 | O91: =AMD!F46/AMD!F49 -> 0.53149647 | P91: AMD | Q91: =K91/L91-1 -> 0.33402826 | R91: =L91/M91-1 -> -0.2195017 | S91: =M91/N91-1 -> -0.37303323 | T91: =N91/O91-1 -> -0.21152774
J92: Qualcomm | K92: =Qualcomm!B59/Qualcomm!B62 -> 0.74897578 | L92: =Qualcomm!C59/Qualcomm!C62 -> 0.74287407 | M92: =Qualcomm!D59/Qualcomm!D62 -> 0.76479019 | N92: =Qualcomm!E59/Qualcomm!E62 -> 0.77678671 | O92: =Qualcomm!F59/Qualcomm!F62 -> 0.77748136 | P92: Qualcomm | Q92: =K92/L92-1 -> 0.0082136533 | R92: =L92/M92-1 -> -0.028656382 | S92: =M92/N92-1 -> -0.01544377 | T92: =N92/O92-1 -> -0.00089346204
A93: YoY Gross Profit Margin Growth (%) | J93: Intel | K93: =Intel!B56/Intel!B60 -> 0.5704224 | L93: =Intel!C56/Intel!C60 -> 0.53953677 | M93: =Intel!D56/Intel!D60 -> 0.50390142 | N93: =Intel!E56/Intel!E60 -> 0.51985473 | O93: =Intel!F56/Intel!F60 -> 0.51634312 | P93: Intel | Q93: =K93/L93-1 -> 0.057244721 | R93: =L93/M93-1 -> 0.070718898 | S93: =M93/N93-1 -> -0.030688015 | T93: =N93/O93-1 -> 0.0068009262
A94: Companies | B94: 2024/23 | C94: 2023/22 | D94: 2022/21 | E94: 2021/20 | F94: AVG | G94: RANK | J94: Embedded | P94: Embedded
A95: NVIDIA | B95: =B86/C86-1 -> 0.27734034 | C95: =C86/D86-1 -> -0.12321358 | D95: =D86/E86-1 -> 0.041450201 | E95: =E86/F86-1 -> 0.0057340833 | F95: =AVERAGE(B95:E95) -> 0.05032776 | G95: =_xlfn.RANK.EQ(F95,F95:F100,0) -> 1 | J95: Companies | K95: 2024 | L95: 2023 | M95: 2022 | N95: 2021 | O95: 2020 | P95: Companies | Q95: 2024/23 | R95: 2023/22 | S95: 2022/21 | T95: 2021/20
A96: AMD | B96: =B87/C87-1 -> 0.070044948 | C96: =C87/D87-1 -> 0.02657404 | D96: =D87/E87-1 -> -0.068842338 | E96: =E87/F87-1 -> 0.083599471 | F96: =AVERAGE(B96:E96) -> 0.02784403 | G96: =_xlfn.RANK.EQ(F96,F95:F100,0) -> 2 | J96: NVIDIA | K96: NA | L96: NA | M96: NA | N96: NA | O96: NA | P96: NVIDIA | Q96: NA | R96: NA | S96: NA | T96: NA
A97: Qualcomm | B97: =B88/C88-1 -> 0.0092608931 | C97: =C88/D88-1 -> -0.037023787 | D97: =D88/E88-1 -> 0.0057170413 | E97: =E88/F88-1 -> -0.052058442 | F97: =AVERAGE(B97:E97) -> -0.018526074 | G97: =_xlfn.RANK.EQ(F97,F95:F100,0) -> 5 | J97: AMD | K97: =AMD!B48/AMD!B49 -> 0.13794842 | L97: =AMD!C48/AMD!C49 -> 0.23461199 | M97: =AMD!D48/AMD!D49 -> 0.19287318 | N97: =AMD!E48/AMD!E49 -> 0.014968967 | O97: =AMD!F48/AMD!F49 -> 0.014647137 | P97: AMD | Q97: =K97/L97-1 -> -0.41201463 | R97: =L97/M97-1 -> 0.21640546 | S97: =M97/N97-1 -> 11.884869 | T97: =N97/O97-1 -> 0.021972186
A98: ARM | B98: =B89/C89-1 -> 0.018308736 | C98: =C89/D89-1 -> -0.079917377 | D98: =D89/E89-1 -> -0.012758608 | E98: =E89/F89-1 -> 0.12924436 | F98: =AVERAGE(B98:E98) -> 0.013719277 | G98: =_xlfn.RANK.EQ(F98,F95:F100,0) -> 4 | J98: Qualcomm | K98: NA | L98: NA | M98: NA | N98: NA | O98: NA | P98: Qualcomm | Q98: NA | R98: NA | S98: NA | T98: NA
A99: TSMC | B99: =B90/C90-1 -> 0.032388828 | C99: =C90/D90-1 -> -0.087321333 | D99: =D90/E90-1 -> 0.15371602 | E99: =E90/F90-1 -> -0.027678762 | F99: =AVERAGE(B99:E99) -> 0.017776188 | G99: =_xlfn.RANK.EQ(F99,F95:F100,0) -> 3 | J99: Intel | K99: =Intel!B57/Intel!B60 -> 0.11001676 | L99: =Intel!C57/Intel!C60 -> 0.10647636 | M99: =Intel!D57/Intel!D60 -> 0.13336188 | N99: =Intel!E57/Intel!E60 -> 0.096995849 | O99: =Intel!F57/Intel!F60 -> 0.090848874 | P99: Intel | Q99: =K99/L99-1 -> 0.033250587 | R99: =L99/M99-1 -> -0.20159825 | S99: =M99/N99-1 -> 0.37492358 | T99: =N99/O99-1 -> 0.067661548
A100: Intel | B100: =B91/C91-1 -> -0.18893137 | C100: =C91/D91-1 -> -0.062060473 | D100: =D91/E91-1 -> -0.18633665 | E100: =E91/F91-1 -> -0.010054589 | F100: =AVERAGE(B100:E100) -> -0.11184577 | G100: =_xlfn.RANK.EQ(F100,F95:F100,0) -> 6 | J100: Automotive | P100: Automotive
J101: Companies | K101: 2024 | L101: 2023 | M101: 2022 | N101: 2021 | O101: 2020 | P101: Companies | Q101: 2024/23 | R101: 2023/22 | S101: 2022/21 | T101: 2021/20
A102: Net Profit Margin (%) | J102: NVIDIA | K102: =NVIDIA!B55/NVIDIA!B57 -> 0.017908145 | L102: =NVIDIA!C55/NVIDIA!C57 -> 0.033476681 | M102: =NVIDIA!D55/NVIDIA!D57 -> 0.021029947 | N102: =NVIDIA!E55/NVIDIA!E57 -> 0.032143928 | O102: =NVIDIA!F55/NVIDIA!F57 -> 0.064114307 | P102: NVIDIA | Q102: =K102/L102-1 -> -0.46505615 | R102: =L102/M102-1 -> 0.5918576 | S102: =M102/N102-1 -> -0.34575677 | T102: =N102/O102-1 -> -0.49864656
A103: Companies | B103: 2024 | C103: 2023 | D103: 2022 | E103: 2021 | F103: 2020 | G103: AVG | H103: RANK | J103: AMD | K103: NA | L103: NA | M103: NA | N103: NA | O103: NA | P103: AMD | Q103: NA | R103: NA | S103: NA | T103: NA
A104: NVIDIA | B104: =NVIDIA!B14/NVIDIA!B6 -> 0.48849348 | C104: =NVIDIA!C14/NVIDIA!C6 -> 0.16193371 | D104: =NVIDIA!D14/NVIDIA!D6 -> 0.3623393 | E104: =NVIDIA!E14/NVIDIA!E6 -> 0.2597901 | F104: =NVIDIA!F14/NVIDIA!F6 -> 0.25609086 | G104: =AVERAGE(B104:F104) -> 0.30572949 | H104: =_xlfn.RANK.EQ(G104,G104:G109,0) -> 2 | J104: Qualcomm | K104: =Qualcomm!B61/Qualcomm!B62 -> 0.087661164 | L104: =Qualcomm!C61/Qualcomm!C62 -> 0.06161543 | M104: =Qualcomm!D61/Qualcomm!D62 -> 0.040050959 | N104: =Qualcomm!E61/Qualcomm!E62 -> 0.036085717 | O104: =Qualcomm!F61/Qualcomm!F62 -> 0.039046868 | P104: Qualcomm | Q104: =K104/L104-1 -> 0.42271447 | R104: =L104/M104-1 -> 0.53842582 | S104: =M104/N104-1 -> 0.10988397 | T104: =N104/O104-1 -> -0.075835811
A105: AMD | B105: =AMD!B13/AMD!B6 -> 0.063641652 | C105: =AMD!C13/AMD!C6 -> 0.037654321 | D105: =AMD!D13/AMD!D6 -> 0.055929833 | E105: =AMD!E13/AMD!E6 -> 0.19240599 | F105: =AMD!F13/AMD!F6 -> 0.25504456 | G105: =AVERAGE(B105:F105) -> 0.12093527 | H105: =_xlfn.RANK.EQ(G105,G104:G109,0) -> 5 | J105: Intel | K105: NA | L105: NA | M105: NA | N105: NA | O105: NA | P105: Intel | Q105: NA | R105: NA | S105: NA | T105: NA
A106: Qualcomm | B106: =Qualcomm!B13/Qualcomm!B5 -> 0.26030491 | C106: =Qualcomm!C13/Qualcomm!C5 -> 0.20189838 | D106: =Qualcomm!D13/Qualcomm!D5 -> 0.29266968 | E106: =Qualcomm!E13/Qualcomm!E5 -> 0.26940952 | F106: =Qualcomm!F13/Qualcomm!F5 -> 0.22090009 | G106: =AVERAGE(B106:F106) -> 0.24903652 | H106: =_xlfn.RANK.EQ(G106,G104:G109,0) -> 3
A107: ARM | B107: =ARM!B8/ARM!B7 -> 0.19765411 | C107: =ARM!C8/ARM!C7 -> 0.094648933 | D107: =ARM!D8/ARM!D7 -> 0.19559537 | E107: =ARM!E8/ARM!E7 -> 0.25009249 | F107: =ARM!F8/ARM!F7 -> 0.26837691 | G107: =AVERAGE(B107:F107) -> 0.20127356 | H107: =_xlfn.RANK.EQ(G107,G104:G109,0) -> 4
A108: TSMC | B108: =TSMC!B10/TSMC!B4 -> 0.35103479 | C108: =TSMC!C10/TSMC!C4 -> 0.38164408 | D108: =TSMC!D10/TSMC!D4 -> 0.44878307 | E108: =TSMC!E10/TSMC!E4 -> 0.37608668 | F108: =TSMC!F10/TSMC!F4 -> 0.38602255 | G108: =AVERAGE(B108:F108) -> 0.38871423 | H108: =_xlfn.RANK.EQ(G108,G104:G109,0) -> 1
A109: Intel | B109: =Intel!B14/Intel!B5 -> -0.35321369 | C109: =Intel!C14/Intel!C5 -> 0.031146271 | D109: =Intel!D14/Intel!D5 -> 0.12709741 | E109: =Intel!E14/Intel!E5 -> 0.25141729 | F109: =Intel!F14/Intel!F5 -> 0.26839354 | G109: =AVERAGE(B109:F109) -> 0.064968165 | H109: =_xlfn.RANK.EQ(G109,G104:G109,0) -> 6
...

Sheet NVIDIA
A1: NVIDIA | AP1: by Geetanjali Jorige
A3: INCOME STATEMENT (GAAP)
A4: Reporting Date | B4: Jan 28, 2024 | C4: Jan 29, 2023 | D4: Jan 30, 2022 | E4: Jan 31, 2021 | F4: Jan 26, 2020
A5: Item (M) | B5: 2024 | C5: 2023 | D5: 2022 | E5: 2021 | F5: 2020
A6: Total Revenue | B6: 60922 | C6: 26974 | D6: 26914 | E6: 16675 | F6: 10918
A7: Cost of Revenue | B7: 16621 | C7: 11618 | D7: 9439 | E7: 6279 | F7: 4150
A8: Gross Profit | B8: =B6-B7 -> 44301 | C8: =C6-C7 -> 15356 | D8: =D6-D7 -> 17475 | E8: =E6-E7 -> 10396 | F8: =F6-F7 -> 6768
A9: Total Operating Expenses | B9: =B47 -> 11329 | C9: =C47 -> 11132 | D9: =D47 -> 7434 | E9: =E47 -> 5864 | F9: =F47 -> 3922
A10: Operating Income (EBIT) | B10: =B8-B9 -> 32972 | C10: =C8-C9 -> 4224 | D10: =D8-D9 -> 10041 | E10: =E8-E9 -> 4532 | F10: =F8-F9 -> 2846
A11: Operating Margin (%) | B11: =B10/B6 -> 0.54121664 | C11: =C10/C6 -> 0.15659524 | D11: =D10/D6 -> 0.37307721 | E11: =E10/E6 -> 0.27178411 | F11: =F10/F6 -> 0.26067045
A12: Income Before Taxes | B12: 33818 | C12: 4181 | D12: 9941 | E12: 4409 | F12: 2970
A13: Income Tax Expense (Benefit) | B13: 4058 | C13: -187 | D13: 189 | E13: 77 | F13: 174
A14: Net Income | B14: 29760 | C14: 4368 | D14: 9752 | E14: 4332 | F14: 2796
A17: BALANCE SHEET
A18: Balance Sheet Item (M) | B18: 2024 | C18: 2023 | D18: 2022 | E18: 2021 | F18: 2020
A19: Cash & Equivalents | B19: 7280 | C19: 3389 | D19: 1990 | E19: 847 | F19: 10896
A20: Total Current Assets | B20: 44345 | C20: 23073 | D20: 28829 | E20: 16055 | F20: 13690
A21: Total Assets | B21: 65728 | C21: 41182 | D21: 44187 | E21: 28791 | F21: 17315
A22: Total Current Liabilities | B22: 10631 | C22: 6563 | D22: 3925 | E22: 3925 | F22: 1784
A23: Long-Term Debt | B23: 8459 | C23: 9703 | D23: 10946 | E23: 5964 | F23: 1991
A24: Total Liabilities | B24: 22750 | C24: 19081 | D24: 17575 | E24: 11898 | F24: 5111
A25: Total Shareholders' Equity | B25: 42978 | C25: 22101 | D25: 26612 | E25: 16893 | F25: 12204
A28: CASH FLOW
A29: Cash Flow/Investing (M) | B29: 2024 | C29: 2023 | D29: 2022 | E29: 2021 | F29: 2020
A30: Cash from Financial Activities | B30: -13633 | C30: -11617 | D30: 1865 | E30: 3804 | F30: -792
A31: Cash from Operating Activities (CFO) | B31: 28090 | C31: 5641 | D31: 9108 | E31: 5822 | F31: 4761
A32: Cash from Investing Activities | B32: -10566 | C32: 7375 | D32: -9830 | E32: -19675 | F32: 6145
A33: Free Cashflow | B33: =B31-ABS(B32) -> 17524 | C33: =C31-ABS(C32) -> -1734 | D33: =D31-ABS(D32) -> -722 | E33: =E31-ABS(E32) -> -13853 | F33: =F31-ABS(F32) -> -1384
A36: INVESTING ACTIVITIES
A37: Investing (M) | B37: 2024 | C37: 2023 | D37: 2022 | E37: 2021 | F37: 2020
A38: Purchases of PP&E & Intangibles (Capex/CFInv) | B38: -1069 | C38: -1833 | D38: -976 | E38: -1128 | F38: -489
A39: Acquisitions, net of cash acquired | B39: -83 | C39: -49 | D39: -263 | E39: -8524 | F39: -4
A42: OPERATIONAL EXPENSES BREAKDOWN
A43: Operating Expenses (M) | B43: 2024 | C43: 2023 | D43: 2022 | E43: 2021 | F43: 2020
A44: Research and development (R&D) | B44: 8675 | C44: 7339 | D44: 5268 | E44: 3924 | F44: 2829
A45: Selling, general and administrative (SG&A) | B45: 2654 | C45: 2440 | D45: 2166 | E45: 1940 | F45: 1093
A46: Acquisition Termination Cost | B46: 0 | C46: 1353 | D46: 0 | E46: 0 | F46: 0
A47: Total Operating Expenses | B47: =B44+B45+B46 -> 11329 | C47: =C44+C45+C46 -> 11132 | D47: =D44+D45+D46 -> 7434 | E47: =E44+E45+E46 -> 5864 | F47: =F44+F45+F46 -> 3922
A50: SEGMENT REVENUE DATA
A51: Segment Revenue (M) | B51: 2024 | C51: 2023 | D51: 2022 | E51: 2021 | F51: 2020
A52: Data Center | B52: 47525 | C52: 15005 | D52: 10613 | E52: 6696 | F52: 2983
A53: Gaming | B53: 10447 | C53: 9067 | D53: 12462 | E53: 7759 | F53: 5518
A54: Professional Visualization | B54: 1553 | C54: 1544 | D54: 2111 | E54: 1053 | F54: 1212
A55: Automotive | B55: 1091 | C55: 903 | D55: 566 | E55: 536 | F55: 700
A56: OEM & Other | B56: 306 | C56: 455 | D56: 1162 | E56: 631 | F56: 505
A57: Total Revenue | B57: =B52+B53+B54+B55+B56 -> 60922 | C57: =C52+C53+C54+C55+C56 -> 26974 | D57: =D52+D53+D54+D55+D56 -> 26914 | E57: =E52+E53+E54+E55+E56 -> 16675 | F57: =F52+F53+F54+F55+F56 -> 10918
A60: KEY FINANCIAL RATIOS
A61: Financial Ratios | B61: 2024 | C61: 2023 | D61: 2022 | E61: 2021 | F61: 2020
A62: Gross Margin (%) | B62: =(B8/B6) -> 0.72717573 | C62: =(C8/C6) -> 0.56928894 | D62: =(D8/D6) -> 0.64929033 | E62: =(E8/E6) -> 0.62344828 | F62: =(F8/F6) -> 0.61989375
A63: Operating Margin (%) | B63: =(B10/B6) -> 0.54121664 | C63: =(C10/C6) -> 0.15659524 | D63: =(D10/D6) -> 0.37307721 | E63: =(E10/E6) -> 0.27178411 | F63: =(F10/F6) -> 0.26067045
A64: Net Profit Margin (%) | B64: =(B14/B6) -> 0.48849348 | C64: =(C14/C6) -> 0.16193371 | D64: =(D14/D6) -> 0.3623393 | E64: =(E14/E6) -> 0.2597901 | F64: =(F14/F6) -> 0.25609086
A66: Year-over-Year Financial Growth
A67: Financial Metric | B67: 2024/23 | C67: 2023/22 | D67: 2022/21 | E67: 2021/20 | F67: 2020/19
A68: Total Revenue | B68: =B6/C6-1 -> 1.2585453 | C68: =C6/D6-1 -> 0.002229323 | D68: =D6/E6-1 -> 0.61403298 | E68: =E6/F6-1 -> 0.52729438 | F68: -0.068
A69: Total Operating Expenses | B69: =B9/C9-1 -> 0.01769673 | C69: =C9/D9-1 -> 0.49744418 | D69: =D9/E9-1 -> 0.26773533 | E69: =E9/F9-1 -> 0.49515553 | F69: =F9/3367-1 -> 0.16483516
A70: Gross Profit | B70: =B8/C8-1 -> 1.884931 | C70: =C8/D8-1 -> -0.12125894 | D70: =D8/E8-1 -> 0.68093497 | E70: =E8/F8-1 -> 0.53605201 | F70: -0.056
A71: Operating Income (EBIT) | B71: =B10/C10-1 -> 6.8058712 | C71: =C10/D10-1 -> -0.57932477 | D71: =D10/E10-1 -> 1.2155781 | E71: =E10/F10-1 -> 0.5924104 | F71: -0.252
A72: Net Income | B72: =B14/C14-1 -> 5.8131868 | C72: =C14/D14-1 -> -0.55209188 | D72: =D14/E14-1 -> 1.2511542 | E72: =E14/F14-1 -> 0.54935622 | F72: -0.326
C74: Revenue by geographic areas
A75: Region | B75: 2024 | C75: 2023 | D75: 2022 | E75: 2021 | F75: 2020
A76: United States | B76: 26966 | C76: 8292 | D76: 4349 | E76: 5044 | F76: 866
A77: Taiwan | B77: 13405 | C77: 6986 | D77: 8544 | E77: 4531 | F77: 3025
A78: China (including Hong Kong) | B78: 10306 | C78: 5785 | D78: 7111 | E78: 3886 | F78: 2731
A79: Other Countries | B79: 10245 | C79: 5911 | D79: 6910 | E79: 5044 | F79: 4276
A80: Total Revenue (Reported) | B80: 60922 | C80: 26974 | D80: 26914 | E80: 16675 | F80: 10918

Sheet AMD
A1: ADVANCED MICRO DEVICES (AMD) INC | AE1: by Gurusharan Kannan
A3: INCOME STATEMENT (GAAP)
A4: Reporting date | B4: Dec 28, 2024 | C4: Dec 30, 2023 | D4: Dec 31, 2022 | E4: Dec 25, 2021 | F4: Dec 26, 2020 | Q4: A steadily growing revenue of AMD for the five years is observed which is supported by gradual increase in the sales cost. This means that AMD is doing really well in terms of quantity and quality and thus, its gross profit is getting higher. The highest revenue in 2023 is mainly attributed by the revenue coming from the company Xilinx, a major acquisition. In 2023 there was a little fluctuation but AMD managed to showcase a good revenue recovery in 2024.
A5: Items (In $ Millions) | B5: 2024 | C5: 2023 | D5: 2022 | E5: 2021 | F5: 2020
A6: Total Revenue (Sales) | B6: 25785 | C6: 22680 | D6: 23601 | E6: 16434 | F6: 9763
A7: Total Cost of Sales | B7: 13060 | C7: 12220 | D7: 12998 | E7: 8505 | F7: 5416
A8: Gross Profit | B8: =B6-B7 -> 12725 | C8: =C6-C7 -> 10460 | D8: =D6-D7 -> 10603 | E8: =E6-E7 -> 7929 | F8: =F6-F7 -> 4347
A9: Total Operating Expenses | B9: =B41 -> 10825 | C9: =C41 -> 10059 | D9: =D41 -> 9339 | E9: =E41 -> 4281 | F9: =F41 -> 2978
A10: Operating Profit | B10: =B8-B9 -> 1900 | C10: =C8-C9 -> 401 | D10: =D8-D9 -> 1264 | E10: =E8-E9 -> 3648 | F10: =F8-F9 -> 1369
A11: Other Income | B11: 181 | C11: 197 | D11: 8 | E11: 55 | F11: -47
A12: Interest expense | B12: -92 | C12: -106 | D12: -88 | E12: -34 | F12: -47 | Q12: Total operating expenses surged threefold from 2020 to 2024. The primary reason for the large increase in operating expenses is the Xilinx acquisition added with its overheads. The decline in 2023 reveals some stabilization and cost-cutting activities, but OpEx rose again in 2024 as AMD's strategic focus shifted to AI and innovation-centered, thus activating its heavy R&D spending. AMD's operating expenses grew by 263% in the period from 2020 to 2024. The company is gradually changing its position from a small player to a large, multi-segment player in the technology industry.
A13: Net Income | B13: 1641 | C13: 854 | D13: 1320 | E13: 3162 | F13: 2490
A14: Comprehensive Income | B14: 1582 | C14: 885 | D14: 1282 | E14: 3142 | F14: 2507
A16: Year-on-Year Change %
A17: Items | B17: 2024/23 | C17: 2023/22 | D17: 2022/21 | E17: 2021/20 | F17: 2020/19
A18: Total Revenue (Sales) | B18: =B6/C6-1 -> 0.13690476 | C18: =C6/D6-1 -> -0.03902377 | D18: =D6/E6-1 -> 0.43610807 | E18: =E6/F6-1 -> 0.68329407 | F18: =F6/6731-1 -> 0.45045313
A19: Total Cost of Sales | B19: =B7/C7-1 -> 0.068739771 | C19: =C7/D7-1 -> -0.059855362 | D19: =D7/E7-1 -> 0.52827748 | E19: =E7/F7-1 -> 0.57034712 | F19: =F7/3863-1 -> 0.40201916
A20: Total Operating Expenses | B20: =B9/C9-1 -> 0.076150711 | C20: =C9/D9-1 -> 0.077096049 | D20: =D9/E9-1 -> 1.1814996 | E20: =E9/F9-1 -> 0.43754197 | F20: =F9/2237-1 -> 0.33124721
A21: Gross Profit | B21: =B8/C8-1 -> 0.2165392 | C21: =C8/D8-1 -> -0.013486749 | D21: =D8/E8-1 -> 0.33724303 | E21: =E8/F8-1 -> 0.82401656 | F21: =F8/2868-1 -> 0.51569038
A22: Operating Profit (Loss) | B22: =B10/C10-1 -> 3.7381546 | C22: =C10/D10-1 -> -0.68275316 | D22: =D10/E10-1 -> -0.65350877 | E22: =E10/F10-1 -> 1.6647188 | F22: =F10/631-1 -> 1.1695721
A23: Net Income | B23: =B13/C13-1 -> 0.92154567 | C23: =C13/D13-1 -> -0.3530303 | D23: =D13/E13-1 -> -0.58254269 | E23: =E13/F13-1 -> 0.26987952 | F23: =F13/341-1 -> 6.3020528 | Q23: After 2022, operating expenses saw a dramatic increase. This was primarily due to major R&D investments, higher adminsitrative costs, and a very significant rise in the amortization costs associated with the Xilinx acquisition. The graph quite vividly indicates that the purchase had a profound effect on AMD’s cost structure, so to speak, the company became heavier but at the same time, it was ready for the long-term innovation and the expansion into new markets.
A25: Long term growth %
A26: Items | B26: 2024/20 | C26: 2023/20 | D26: 2022/20 | E26: 2021/20 | F26: 2020
A27: Total Revenue (Sales) | B27: =B6/F6-1 -> 1.6410939 | C27: =C6/F6-1 -> 1.3230564 | D27: =D6/F6-1 -> 1.4173922 | E27: =E6/F6-1 -> 0.68329407 | F27: =F6/F6-1 -> 0
A28: Total Cost of Sales | B28: =B7/F7-1 -> 1.4113737 | C28: =C7/F7-1 -> 1.2562777 | D28: =D7/F7-1 -> 1.3999261 | E28: =E7/F7-1 -> 0.57034712 | F28: =F7/F7-1 -> 0
A29: Total Operating Expenses | B29: =B9/F9-1 -> 2.6349899 | C29: =C9/F9-1 -> 2.3777703 | D29: =D9/F9-1 -> 2.1359973 | E29: =E9/F9-1 -> 0.43754197 | F29: =F8/F8-1 -> 0
A30: Gross Profit | B30: =B8/F8-1 -> 1.9273062 | C30: =C8/F8-1 -> 1.4062572 | D30: =D8/F8-1 -> 1.4391534 | E30: =E8/F8-1 -> 0.82401656 | F30: =F9/F9-1 -> 0
A31: Operating Profit (Loss) | B31: =B10/F10-1 -> 0.38787436 | C31: =C10/F10-1 -> -0.70708546 | D31: =D10/F10-1 -> -0.07669832 | E31: =E10/F10-1 -> 1.6647188 | F31: =F10/F10-1 -> 0
A32: Net Income | B32: =B13/F13-1 -> -0.34096386 | C32: =C13/F13-1 -> -0.65702811 | D32: =D13/F13-1 -> -0.46987952 | E32: =E13/F13-1 -> 0.26987952 | F32: =F11/F11-1 -> 0
Q33: Operating margins go up steadily until 2021, then they decline drastically in 2022 and 2023 and finally recover a little in 2024. The decline is closely related to the increase in operating costs caused by the Xilinx acquisition. Although sales are still good, the additional costs will impact AMD's profit negatively in the short term. The slight increase in 2024 indicates the firm is gradually taking in these costs.
A34: Operating Expenses
A35: Items (In $ Millions) | B35: 2024 | C35: 2023 | D35: 2022 | E35: 2021 | F35: 2020
A36: Research and development | B36: 6456 | C36: 5872 | D36: 5005 | E36: 2845 | F36: 1983
A37: Marketing, general and administrative | B37: 2783 | C37: 2352 | D37: 2336 | E37: 1448 | F37: 995
A38: Amortization of acquisition-related intangibles | B38: 1448 | C38: 1869 | D38: 2100 | E38: 0 | F38: 0
A39: Restructuring charges | B39: 186 | C39: - | D39: - | E39: 0 | F39: 0
A40: Licensing gain | B40: -48 | C40: -34 | D40: -102 | E40: -12 | F40: 0
A41: Total | B41: =SUM(B36:B40) -> 10825 | C41: =SUM(C36:C40) -> 10059 | D41: =SUM(D36:D40) -> 9339 | E41: =SUM(E36:E40) -> 4281 | F41: =SUM(F36:F40) -> 2978
A43: Segmented Revenue Data
A44: Segments (in $ millions) | B44: 2024 | C44: 2023 | D44: 2022 | E44: 2021 | F44: 2020 | Q44: Net profit margin during the year 2020-2021 was very high but suddenly falls starting from 2022. The main reasons for the decrease are the high amortization, increased R&D, and the market conditions. Margins do not go back to the same level as pre-acquisition phase even in 2024, hinting at the long-term financial effect of Xilinx. Nevertheless, the upward trend in recovery suggests better stability.
A45: Data Center | B45: 12579 | C45: 6496 | D45: 6043 | E45: 3694 | F45: 1685
A46: Client | B46: 7054 | C46: 4651 | D46: 6201 | E46: 6887 | F46: 5189
A47: Gaming | B47: 2595 | C47: 6212 | D47: 6805 | E47: 5607 | F47: 2746
A48: Embedded | B48: 3557 | C48: 5321 | D48: 4552 | E48: 246 | F48: 143
A49: Total | B49: =SUM(B45:B48) -> 25785 | C49: =SUM(C45:C48) -> 22680 | D49: =SUM(D45:D48) -> 23601 | E49: =SUM(E45:E48) -> 16434 | F49: =SUM(F45:F48) -> 9763
A51: Investing Activities (CFInv)
A52: Items (In $ Millions) | B52: 2024 | C52: 2023 | D52: 2022 | E52: 2021 | F52: 2020
A53: Purchases of property and equipment | B53: -636 | C53: -546 | D53: -450 | E53: -301 | F53: -294 | Q53: Gross margins are seen consistently stable and still in a good range all throughout the five years, where they are within the range of 40-50%. This illustrates that the main activity of AMD has not been affected by the market fluctuations and still being competitive. The slowly transitioning up in 2024 points at a better product mix (high-margin from data-center segment) and better pricing.
A54: Acquisitions, net of cash acquired | B54: -548 | C54: -131 | D54: -1544 | E54: 0 | F54: 0
A55: Cash received from acquisition of Xilinx | B55: 0 | C55: 0 | D55: 2366 | E55: 0 | F55: 0
A56: Payments to acquire interest to subsidiaries and affliates | B56: -17 | C56: 0 | D56: 0 | E56: 0 | F56: 0
A57: Payments to acquire other investments | B57: -341 | C57: -11 | D57: -5 | E57: 0 | F57: 0
A58: Other | B58: 2 | C58: 0 | D58: -11 | E58: -7 | F58: 0
A59: Total CapEx | B59: =SUM(B53:B58) -> -1540 | C59: =SUM(C53:C58) -> -688 | D59: =SUM(D53:D58) -> 356 | E59: =SUM(E53:E58) -> -308 | F59: =SUM(F53:F58) -> -294
A61: Free Cash Flow
A62: Items (In $ Millions) | B62: 2024 | C62: 2023 | D62: 2022 | E62: 2021 | F62: 2020
A63: Cash from Operating Activities (CFO) | B63: 3041 | C63: 1667 | D63: 3565 | E63: 3521 | F63: 1071
A64: Cash used in Investing Activities (CapEx/CFInv) | B64: =B59 -> -1540 | C64: =C59 -> -688 | D64: =D59 -> 356 | E64: =E59 -> -308 | F64: =F59 -> -294
A65: Cash used in Financing Activities | B65: -2062 | C65: -1146 | D65: -3624 | E65: -1895 | F65: 6 | Q65: Over the five years, AMD has always spent cash on investing activities, but the pattern is a bit inconsistent. The highest point in 2022 represents the purchase of Xilinx and the associated expenses. Investments cash outflow has a pronounced decrease in 2023 and 2024 after the acquisition suggesting that AMD has already returned to a more routine cycle of capital investment. The investment pattern indicates high investments during the periods of strategic expansion, followed by stabilization through the years 2023 and 2024.
A66: Free Cash Flow (FCF) | B66: =B63-ABS(B64) -> 1501 | C66: =C63-ABS(C64) -> 979 | D66: =D63-ABS(D64) -> 3209 | E66: =E63-ABS(E64) -> 3213 | F66: =F63-ABS(F64) -> 777
A68: Key Financial Ratios
A69: Financial Metric (%) | B69: 2024 | C69: 2023 | D69: 2022 | E69: 2021 | F69: 2020
A70: Gross Profit Margin | B70: =B8/B6 -> 0.49350398 | C70: =C8/C6 -> 0.46119929 | D70: =D8/D6 -> 0.44926062 | E70: =E8/E6 -> 0.48247536 | F70: =F8/F6 -> 0.44525248
A71: Operating Margin | B71: =B10/B6 -> 0.073686252 | C71: =C10/C6 -> 0.017680776 | D71: =D10/D6 -> 0.053557053 | E71: =E10/E6 -> 0.22197882 | F71: =F10/F6 -> 0.14022329
A72: Net Profit Margin | B72: =B13/B6 -> 0.063641652 | C72: =C13/C6 -> 0.037654321 | D72: =D13/D6 -> 0.055929833 | E72: =E13/E6 -> 0.19240599 | F72: =F13/F6 -> 0.25504456
A74: Geographical Segmented Revenue
A75: Regions (in $ millions) | B75: 2024 | C75: 2023 | D75: 2022 | E75: 2021 | F75: 2020 | Q75: FCF shows a dramatic increase in 2021, which is the result of high revenues and low capital intensity. After the year 2022, FCF turns into a more volatile stream where it will drop drastically in 2023 due to the combination of bad PC demand and increased costs. However, the situation improves in 2024 when the company gets the advantage of increased data center demand and improved cost control. Overall, AMD stays FCF-positive but the ups and downs reveal the extent to which the company is influenced by the market's ups and downs as well as big mergers and acquisitions.
A76: United States | B76: 8693 | C76: 7837 | D76: 8049 | E76: 4656 | F76: 2294
A77: China (including Hong Kong) | B77: 6231 | C77: 3417 | D77: 5207 | E77: 4096 | F77: 2329
A78: Singapore | B78: 3614 | C78: 2231 | D78: 21 | E78: 1389 | F78: 1096
A79: Taiwan | B79: 3301 | C79: 1841 | D79: 2369 | E79: 2091 | F79: 1187
A80: Japan | B80: 1767 | C80: 4629 | D80: 4177 | E80: 2381 | F80: 1033
A81: Europe | B81: 1625 | C81: 2030 | D81: 1773 | E81: 1249 | F81: 1108
A82: Other Regions | B82: 554 | C82: 695 | D82: 646 | E82: 572 | F82: 716
A83: Total | B83: =SUM(B76:B82) -> 25785 | C83: =SUM(C76:C82) -> 22680 | D83: =SUM(D76:D82) -> 22242 | E83: =SUM(E76:E82) -> 16434 | F83: =SUM(F76:F82) -> 9763
Q87: The Data Center has emerged as the most powerful growth driver, with a tremendous increase in 2024, and surpassing all the other segments. The Client revenue sees a small recovery in 2024, after a post-pandemic dip in 2022-2023, which is indicative of a stable PC market. Gaming reached the highest revenue in 2022 and then it was declining till the end of 2024. Embedded, with Xilinx's support, peaks in 2022 and 2023, then it calms down in 2024. This transition reveals that AMD is tactically moving from consumer to premium enterprise and AI premises.
Q100: The cash flow from operations (CFO) trend shows an increase up to 2022, a decrease in 2023, and finally again a rise in 2024 — it is thus reflecting business cycles. On the other hand, cash outflows for investing activities (CFInv) soar in 2022 (acquisiton of Xilinx) but become less significant afterwards, which in turn positively affects cash sustainability. Cash flow used for financing was characterized by large outflows in 2022-2023, which were indicative of debt repayments and adjustments related to acquisition. Free cash flow goes along with the general trend of CFO but drops significantly in the expensive years. Hence, the pattern indicates that AMD continues to be financially sustainable and in GROWTH stage and regained its strength by 2024.

Sheet Qualcomm
A1: QUALCOMM | P1: by Manav Dharora
A2: Income Statement
A3: Reporting Date | B3: 28th Sept 2024 | C3: 24th Sept 2023 | D3: 25th Sept 2022 | E3: 26th Sept 2021 | F3: 27th Sept 2020
A4: Item | B4: 2024 | C4: 2023 | D4: 2022 | E4: 2021 | F4: 2020
A5: Total Revenues (Sales) | B5: 38962 | C5: 35820 | D5: 44200 | E5: 33566 | F5: 23531
A6: Total Cost of Revenue | B6: 17060 | C6: 15869 | D6: 18635 | E6: 14262 | F6: 9255
A7: Gross Profit | B7: 21902 | C7: 19951 | D7: 25565 | E7: 19304 | F7: 14276
A8: Total Operating Expenses | B8: =B34 -> 13358 | C8: =C34 -> 13110 | D8: =D34 -> 12526 | E8: =E34 -> 11097 | F8: =F34 -> 9442
A9: Operating Profit (Loss) (EBIT) | B9: =SUM(B7,-B8) -> 8544 | C9: =SUM(C7,-C8) -> 6841 | D9: =SUM(D7,-D8) -> 13039 | E9: =SUM(E7,-E8) -> 8207 | F9: =SUM(F7,-F8) -> 4834
A10: Operating Margin | B10: =B9/B5 -> 0.21929059 | C10: =C9/C5 -> 0.19098269 | D10: =D9/D5 -> 0.295 | E10: =E9/E5 -> 0.24450337 | F10: =F9/F5 -> 0.20543113
A11: Other Income (expense), net | B11: 962 | C11: 349 | D11: (372) | E11: 1044 | F11: 66
A12: Interest expense | B12: (697) | C12: (694) | D12: (490) | E12: (559) | F12: (602)
A13: Net Income | B13: 10142 | C13: 7232 | D13: 12936 | E13: 9043 | F13: 5198
A14: Comprehensive Income | B14: 10371 | C14: 7612 | D14: 12786 | E14: 8964 | F14: 5305
A15: Net Profit Margin | B15: 0.26 | C15: 0.2 | D15: 0.29 | E15: 0.27 | F15: 0.23
A17: Item | B17: 2024 | C17: 2023 | D17: 2022 | E17: 2021 | F17: 2020
A18: Total Revenue (In US millions) | B18: 38962 | C18: 35820 | D18: 44200 | E18: 33566 | F18: 23531
A19: Total Cost of Sales | B19: 17060 | C19: 15869 | D19: 18635 | E19: 14262 | F19: 9255
A21: Year-on-Year Change % | B21: 2024/23 | C21: 2023/22 | D21: 2022/21 | E21: 2021/20
A22: Total Revenues (Sales) | B22: =(B5-C5)/C5 -> 0.08771636 | C22: =(C5-D5)/D5 -> -0.18959276 | D22: =(D5-E5)/E5 -> 0.31680868 | E22: =(E5-F5)/F5 -> 0.42645871
A23: Total Cost of Sales | B23: =(B6-C6)/C6 -> 0.075051988 | C23: =(C6-D6)/D6 -> -0.14843037 | D23: =(D6-E6)/E6 -> 0.30661899 | E23: =(E6-F6)/F6 -> 0.54100486
A24: Total Operating Expenses | B24: =(B8-C8)/C8 -> 0.018916857 | C24: =(C8-D8)/D8 -> 0.046623024 | D24: =(D8-E8)/E8 -> 0.12877354 | E24: =(E8-F8)/F8 -> 0.17528066
A25: Gross Profit | B25: =(B7-C7)/C7 -> 0.097789584 | C25: =(C7-D7)/D7 -> -0.21959711 | D25: =(D7-E7)/E7 -> 0.32433692 | E25: =(E7-F7)/F7 -> 0.3521995
A26: Operating Profit (Loss) (EBIT) | B26: =(B9-C9)/C9 -> 0.24894021 | C26: =(C9-D9)/D9 -> -0.4753432 | D26: =(D9-E9)/E9 -> 0.58876569 | E26: =(E9-F9)/F9 -> 0.69776583
A27: Net Income | B27: =(B13-C13)/C13 -> 0.40237832 | C27: =(C13-D13)/D13 -> -0.44094001 | D27: =(D13-E13)/E13 -> 0.43049873 | E27: =(E13-F13)/F13 -> 0.73970758
A29: Operating Expenses
A30: Item | B30: 2024 | C30: 2023 | D30: 2022 | E30: 2021 | F30: 2020
A31: Research and development | B31: 8893 | C31: 8818 | D31: 8194 | E31: 7176 | F31: 5975
A32: Marketing, general and administrative | B32: 2759 | C32: 2483 | D32: 2570 | E32: 2339 | F32: 2074
A33: Depreciation and amortization expense | B33: 1706 | C33: 1809 | D33: 1762 | E33: 1582 | F33: 1393
A34: Total | B34: =SUM(B31:B33) -> 13358 | C34: =SUM(C31:C33) -> 13110 | D34: =SUM(D31:D33) -> 12526 | E34: =SUM(E31:E33) -> 11097 | F34: =SUM(F31:F33) -> 9442
A37: Investing Activities (CapEx)
A38: Item | B38: 2024 | C38: 2023 | D38: 2022 | E38: 2021 | F38: 2020
A39: Purchases of plant, property and equipment | B39: -1041 | C39: -1450 | D39: -2262 | E39: -1888 | F39: -1407
A40: Purchases of debt and equity marketable securities | B40: -5069 | C40: -668 | D40: -1414 | E40: -5907 | F40: -6213
A41: Proceeds from sales and maturities of debt and equity marketable securities | B41: 2677 | C41: 1566 | D41: 2622 | E41: 5555 | F41: 2399
A42: Acquisitions and other investments, net of cash acquired | B42: -254 | C42: -235 | D42: -4912 | E42: -1377 | F42: -185
A43: Proceeds from sales of property, plant and equipment | B43: 10 | C43: 127 | D43: 5 | E43: 3 | F43: -
A44: Proceeds from other investments | B44: 88 | C44: 20 | D44: 132 | E44: 320 | F44: 100
A45: Other items | B45: -36 | C45: 19 | D45: 41 | E45: -62 | F45: 43
A46: Net cash provided by investing activities from discontinued operations | B46: 2 | C46: 1383 | D46: -16 | E46: - | F46: -
A47: Net cash (used) provided by investing activities | B47: -3623 | C47: 762 | D47: -5804 | E47: -3356 | F47: -5263
A49: Free Cash Flow
A50: Item | B50: 2024 | C50: 2023 | D50: 2022 | E50: 2021 | F50: 2020
A51: Cash from Operating Activities (CFO) | B51: 12202 | C51: 11299 | D51: 9096 | E51: 10536 | F51: 5814
A52: Cash used in Investing Activities (CapEx/CFInv) | B52: -3623 | C52: 762 | D52: -5804 | E52: -3356 | F52: -5263
A53: Cash used in Financing Activities | B53: -9269 | C53: -6663 | D53: -7196 | E53: -6798 | F53: -5707
A54: Free Cash Flow (FCF) | B54: 8579 | C54: 12061 | D54: 3292 | E54: 7180 | F54: 551
A56: Segmented Revenue Data
A57: Segments | B57: 2024 | C57: 2023 | D57: 2022 | E57: 2021 | F57: 2020
A58: QCT
A59: Handsets | B59: 24863 | C59: 22570 | D59: 28815 | E59: 20988 | F59: 12823
A60: IoT (internet of things) | B60: 5423 | C60: 5940 | D60: 7353 | E60: 5056 | F60: 3026
A61: Automotive | B61: 2910 | C61: 1872 | D61: 1509 | E61: 975 | F61: 644
A62: Total Revenues | B62: 33196 | C62: 30382 | D62: 37677 | E62: 27019 | F62: 16493
A64: QTL
A65: Total Licensing revenues | B65: 5572 | C65: 5306 | D65: 6358 | E65: 6320 | F65: 5028
A67: QSI
A68: Equipment and services revenues | B68: 18 | C68: 28 | D68: 31 | E68: 45 | F68: 36
F78: `

Sheet ARM
A1: ARM | R1: by Gloria
A3: INCOME STATEMENT
A4: FISCAL YEAR END | B4: 31 March 2025 | C4: 31 March 2024 | D4: 31 March 2023 | E4: 31 March 2022 | F4: 31 March 2021
A5: Financial Metric | B5: FY2024 | C5: FY2023 | D5: FY2022 | E5: FY2021 | F5: FY2020
A7: Total Revenue | B7: 4007 | C7: 3233 | D7: 2679 | E7: 2703 | F7: 2027
A8: Net Income | B8: 792 | C8: 306 | D8: 524 | E8: 676 | F8: 544
A9: Cost of Revenue | B9: -121 | C9: -154 | D9: -106 | E9: -131 | F9: -145
A10: Gross Profit | B10: 3886 | C10: 3079 | D10: 2773 | E10: 2834 | F10: 1882
A11: Total Operating Expenses | B11: =B36 -> 3055 | C11: =C36 -> 2968 | D11: =D36 -> 1902 | E11: =E36 -> 1939 | F11: =F36 -> 1643
A12: Operating Income (EBIT) | B12: 831 | C12: 111 | D12: 671 | E12: 633 | F12: 239
A13: Operating Margin (%) | B13: =B12/B7 -> 0.20738707 | C13: =C12/C7 -> 0.034333436 | D13: =D12/D7 -> 0.25046659 | E13: =E12/E7 -> 0.23418424 | F13: =F12/F7 -> 0.11790824
A14: Income Before Taxes | B14: 720 | C14: 212 | D14: 671 | E14: 786 | F14: 697
A15: Income Tax Expense (Benefit) | B15: 72 | C15: 94 | D15: -147 | E15: -110 | F15: -153
A18: CASH FLOW
A19: Financial Metric | B19: FY2024 | C19: FY2023 | D19: FY2022 | E19: FY2021 | F19: FY2020
A21: FREE CASH FLOW | B21: =B24+B23 -> 362 | C21: =C24+C23 -> 574 | D21: =D24+D23 -> 601 | E21: =E24+E23 -> -161 | F21: =F24+F23 -> 893
A22: Net cash provided by (used for) financing activities | B22: -202 | C22: -208 | D22: -42 | E22: -32 | F22: -789
A23: Net cash provided by (used for) investing activities | B23: -35 | C23: -516 | D23: -138 | E23: -619 | F23: -340
A24: Net cash provided by (used for) operating activities | B24: 397 | C24: 1090 | D24: 739 | E24: 458 | F24: 1233
A25: Effect of foreign exchange rate changes on cash and cash equivalents | B25: 2 | C25: 3 | D25: -9 | E25: -17 | F25: 1
A26: Net increase (decrease) in cash and cash equivalents | B26: 162 | C26: 369 | D26: 550 | E26: -210 | F26: 105
A29: OPERATING EXPENSES
A30: Financial Metric | B30: FY2024 | C30: FY2023 | D30: FY2022 | E30: FY2021 | F30: FY2020
A32: Research and Development | B32: 2071 | C32: 1979 | D32: 1133 | E32: 995 | F32: 814
A33: Impairment Of Long Live Assets | E33: 21 | F33: 3
A34: Selling,general and administrative | B34: 984 | C34: 983 | D34: 762 | E34: 897 | F34: 826
A35: Disposal , restructuring and other operating expense | C35: 6 | D35: 7 | E35: 26
A36: Operating Expense | B36: =SUM(B32:B35) -> 3055 | C36: =SUM(C32:C35) -> 2968 | D36: =SUM(D32:D35) -> 1902 | E36: =SUM(E32:E35) -> 1939 | F36: =SUM(F32:F35) -> 1643
A40: INVESTING ACTIVITIES
A41: Financial Metric | B41: FY2024 | C41: FY2023 | D41: FY2022 | E41: FY2021 | F41: FY2020
A43: Purchase of plant ,property and equipment | B43: 219 | C43: 74 | D43: 34 | E43: -103 | F43: -142
A44: Purchase of intangible assets | B44: 20 | C44: 69 | D44: 78 | E44: -88 | F44: -38
A45: Investment In Associates | C45: -2 | D45: 0 | E45: -4 | F45: -8
A46: Purchase Of trading investments | B46: 57 | C46: -11 | D46: 6 | E46: -45 | F46: -47
A47: Payments for financial assets | D47: -29 | E47: -2
A48: TOTAL | B48: =SUM(B43,B45,B44,B46,B47) -> 296 | C48: =SUM(C43,C45,C44,C46,C47) -> 130 | D48: =SUM(D43,D45,D44,D46,D47) -> 89 | E48: =SUM(E43,E45,E44,E46,E47) -> -242 | F48: =SUM(F43,F45,F44,F46,F47) -> -235
A50: Financial Metric | B50: 2025-24 | C50: 2024-23 | D50: 2023-22 | E50: 2022-21 | F50: 2021-20
A51: Gross Margin | B51: =B10/B7 -> 0.96980285 | C51: =C10/C7 -> 0.95236622 | D51: =D10/D7 -> 1.0350877 | E51: =E10/E7 -> 1.0484647 | F51: =F10/F7 -> 0.92846571
A52: Operating Margin | B52: =B12/B7 -> 0.20738707 | C52: =C12/C7 -> 0.034333436 | D52: =D12/D7 -> 0.25046659 | E52: =E12/E7 -> 0.23418424 | F52: =F12/F7 -> 0.11790824
A53: Profit Margin | B53: =B8/B7 -> 0.19765411 | C53: =C8/C7 -> 0.094648933 | D53: =D8/D7 -> 0.19559537 | E53: =E8/E7 -> 0.25009249 | F53: =F8/F7 -> 0.26837691
A55: % Change | B55: 2024 | C55: 2023 | D55: 2022 | E55: 2021
A56: Revenue | B56: =B7/C7-1 -> 0.23940612 | C56: =C7/D7-1 -> 0.20679358 | D56: =D7/E7-1 -> -0.0088790233 | E56: =E7/F7-1 -> 0.33349778
A57: Cost Of Sales | B57: =B9/C9-1 -> -0.21428571 | C57: =C9/D9-1 -> 0.45283019 | D57: =D9/E9-1 -> -0.19083969 | E57: =E9/F9-1 -> -0.096551724
A58: Operating Expenses | B58: =B11/C11-1 -> 0.029312668 | C58: =C11/D11-1 -> 0.56046267 | D58: =D11/E11-1 -> -0.019082001 | E58: =E11/F11-1 -> 0.18015825
A59: Gross Profit | B59: =B10/C10-1 -> 0.26209808 | C59: =C10/D10-1 -> 0.1103498 | D59: =D10/E10-1 -> -0.021524347 | E59: =E10/F10-1 -> 0.50584485
A60: Net Income | B60: =B8/C8-1 -> 1.5882353 | C60: =C8/D8-1 -> -0.41603053 | D60: =D8/E8-1 -> -0.22485207 | E60: =E8/F8-1 -> 0.24264706
A63: GEOGRAPHICAL LOCATION | B63: 2024 | C63: 2023 | D63: 2022 | E63: 2021 | F63: 2020
A64: UNITED STATES OF AMERICA | B64: 1716 | C64: 1405 | D64: 1088 | E64: 1242 | F64: 821
A65: PRC | B65: 748 | C65: 700 | D65: 657 | E65: 476 | F65: 503
A66: TAIWAN | B66: 629 | C66: 521 | D66: 359 | E66: 431 | F66: 378
A67: REPUBLIC OF KOREA | B67: 324 | C67: 307 | D67: 240 | E67: 226 | F67: 214
A68: OTHER | B68: 586 | C68: 294 | D68: 333 | E68: 327 | F68: 125
B70: 2024 | C70: 2023 | D70: 2022 | E70: 2021 | F70: 2020
A71: Licensing and Other Revenues | B71: 1839 | C71: 1431 | D71: 1129 | E71: 1213 | F71: 1123
A72: Royalty Revenue | B72: 2168 | C72: 1802 | D72: 1550 | E72: 1490 | F72: 904
B75: 2024 | C75: 2023 | D75: 2022 | E75: 2021 | F75: 2020
A76: Total Revenue | B76: 4007 | C76: 3233 | D76: 2679 | E76: 2703 | F76: 2027
A77: Royalty% of total | B77: =B72/B76 -> 0.54105316 | C77: =C72/C76 -> 0.55737705 | D77: =D72/D76 -> 0.57857409 | E77: =E72/E76 -> 0.55123936 | F77: =F72/F76 -> 0.44597928
A78: Licensing and Other Revenues % of total | B78: =B71/B76 -> 0.45894684 | C78: =C71/C76 -> 0.44262295 | D78: =D71/D76 -> 0.42142591 | E78: =E71/E76 -> 0.44876064 | F78: =F71/F76 -> 0.55402072
A81: Financial Metric | B81: 2025-24 | C81: 2024-23 | D81: 2023-22 | E81: 2022-21 | F81: 2021-20
A82: Operating Margin | B82: =B12/B7 -> 0.20738707 | C82: =C12/C7 -> 0.034333436 | D82: =D12/D7 -> 0.25046659 | E82: =E12/E7 -> 0.23418424 | F82: =F12/F7 -> 0.11790824

Sheet TSMC
A1: TSMC | G1: by Ting Hsuan Huang
A2: INCOME STATEMENT
A3: <IFRS> (Unit: NT$ billion) | B3: FY2024 | C3: FY2023 | D3: FY2022 | E3: FY2021 | F3: FY2020
A4: Revenue (Total Sales) | B4: 2894.3 | C4: 2161.7 | D4: 2263.9 | E4: 1587.4 | F4: 1339.3
A5: Cost of sales | B5: 1270 | C5: 986.6 | D5: 915.5 | E5: 767.9 | F5: 628.1
A6: Gross profit | B6: 1624.3 | C6: 1175.1 | D6: 1348.4 | E6: 819.5 | F6: 711.1
A7: Operating profit | B7: 1322.1 | C7: 921.5 | D7: 1121.3 | E7: 650 | F7: 566.8
A8: EBIDTA | B8: 1594 | C8: 1224 | D8: 1389 | E8: 948 | F8: 838
A9: Profit before income taxes | B9: 1405.8 | C9: 979 | D9: 1144 | E9: 663.1 | F9: 585
A10: Net Income | B10: 1016 | C10: 825 | D10: 1016 | E10: 597 | F10: 517
B13: FY2024 | C13: FY2023 | D13: FY2022 | E13: FY2021 | F13: FY2020
A14: Operating Margin | B14: =B7/B4 -> 0.45679439 | C14: =C7/C4 -> 0.42628487 | D14: =D7/D4 -> 0.49529573 | E14: =E7/E4 -> 0.40947461 | F14: =F7/F4 -> 0.42320615
A15: Gross Profit Margin | B15: =B6/B4 -> 0.56120651 | C15: =C6/C4 -> 0.54359994 | D15: =D6/D4 -> 0.59560935 | E15: =E6/E4 -> 0.51625299 | F15: =F6/F4 -> 0.530949
A16: Net Profit Margin | B16: =B10/B4 -> 0.35103479 | C16: =C10/C4 -> 0.38164408 | D16: =D10/D4 -> 0.44878307 | E16: =E10/E4 -> 0.37608668 | F16: =F10/F4 -> 0.38602255
A19: Year-on-Year (%) Change | B19: FY2024-23 | C19: FY2023-22 | D19: FY2022-21 | E19: FY2021-20
A20: Revenue | B20: =B4/C4-1 -> 0.33889994 | C20: =C4/D4-1 -> -0.045143337 | D20: =D4/E4-1 -> 0.42616858 | E20: =E4/F4-1 -> 0.18524602
A21: Cost of sales | B21: =B5/C5-1 -> 0.28724914 | C21: =C5/D5-1 -> 0.07766248 | D21: =D5/E5-1 -> 0.19221253 | E21: =E5/F5-1 -> 0.22257602
A22: Gross profit | B22: =B6/C6-1 -> 0.38226534 | C22: =C6/D6-1 -> -0.12852269 | D22: =D6/E6-1 -> 0.64539353 | E22: =E6/F6-1 -> 0.15243988
A23: Operating profit | B23: =B7/C7-1 -> 0.43472599 | C23: =C7/D7-1 -> -0.17818603 | D23: =D7/E7-1 -> 0.72507692 | E23: =E7/F7-1 -> 0.14678899
A24: Profit before income taxes | B24: =B9/C9-1 -> 0.43595506 | C24: =C9/D9-1 -> -0.14423077 | D24: =D9/E9-1 -> 0.72522998 | E24: =E9/F9-1 -> 0.13350427
A27: Operating Expenses | B27: FY2024 | C27: FY2023 | D27: FY2022 | E27: FY2021 | F27: FY2020
A28: R&D ( research and development expenses) | B28: 198.9 | C28: 179.6 | D28: 163.9 | E28: 115.5 | F28: 97.1
A29: G&A ( general and administrative expenses) | B29: 54.9 | C29: 46.8 | D29: 41.5 | E29: 33.3 | F29: 28.4
A30: Other operating income (loss), net | B30: -1.2 | C30: 0.2 | D30: -0.4 | E30: -0.3 | F30: -0.2
A31: Total Operating Expenses | B31: =SUM(B28:B30) -> 252.6 | C31: =SUM(C28:C30) -> 226.6 | D31: =SUM(D28:D30) -> 205 | E31: =SUM(E28:E30) -> 148.5 | F31: =SUM(F28:F30) -> 125.3
A34: Investing | B34: FY2024 | C34: FY2023 | D34: FY2022 | E34: FY2021 | F34: FY2020
A35: Property & equipment | B35: -635.9 | C35: -545.7 | D35: -450.9 | E35: -301.1 | F35: -294.1
A36: Intangible assets | B36: -6.1 | C36: -6 | D36: -5.7 | E36: -6.6 | F36: -5
A37: Other | B37: -47.6 | C37: -33.2 | D37: -27.4 | E37: -24.2 | F37: -49.7
A38: Total | B38: =SUM(B35:B37) -> -689.6 | C38: =SUM(C35:C37) -> -584.9 | D38: =SUM(D35:D37) -> -484 | E38: =SUM(E35:E37) -> -331.9 | F38: =SUM(F35:F37) -> -348.8
A40: Cash Flow Summary | B40: FY2024 | C40: FY2023 | D40: FY2022 | E40: FY2021 | F40: FY2020
A41: Cash Flow from Operating Activities (CFO) | B41: 1826.2 | C41: 1242 | D41: 1610.6 | E41: 1112.2 | F41: 822.7
A42: Cash Flow from Investing Activities (CFInv) | B42: -1014.9 | C42: -906.1 | D42: -1190.9 | E42: -836.4 | F42: -505.8
A43: Cash used in Financing Activities（CFF） | B43: -1999.4 | C43: -2102.8 | D43: -3631.2 | E43: -2038.5 | F43: -1840.2
A44: Free Cash Flow (FCF = CFO - CFInv) | B44: =B41-ABS(B42) -> 811.3 | C44: =C41-ABS(C42) -> 335.9 | D44: =D41-ABS(D42) -> 419.7 | E44: =E41-ABS(E42) -> 275.8 | F44: =F41-ABS(F42) -> 316.9
A47: Segmentation | B47: 2024 (USD mn) | C47: 2023 (USD mn) | D47: 2022 (USD mn) | E47: 2021 (USD mn) | F47: 2020 (USD mn)
A48: High Performance Computing | B48: 45502.2 | C48: 30100 | D48: 31283 | E48: 20979 | F48: 15015
A49: Smartphone | B49: 31227 | C49: 26600 | D49: 29757 | E49: 24948 | F49: 21840
A50: Internet of Things | B50: 5353.2 | C50: 5600 | D50: 6867 | E50: 4536 | F50: 3640
A51: Automotive | B51: 4461 | C51: 4200 | D51: 3815 | E51: 2268 | F51: 1365
A52: DCE | B52: 892.2 | C52: 1400 | D52: 2289 | E52: 2268 | F52: 1820
A53: Others | B53: 1784.4 | C53: 2100 | D53: 2289 | E53: 1701 | F53: 1820
A54: Total | B54: 89220 | C54: 70000 | D54: 76300 | E54: 56700 | F54: 45500

Sheet Intel
A1: INTEL | G1: by Alperen Onal
A3: Income Statement
A4: Financial Metrics | B4: 2024 | C4: 2023 | D4: 2022 | E4: 2021 | F4: 2020
A5: Total Revenues (Sales) | B5: 53101 | C5: 54228 | D5: 63054 | E5: 79024 | F5: 77867
A6: Total Cost of Sales | B6: 34877 | C6: 31282 | D6: 34608 | E6: 35209 | F6: 34255
A7: Gross Profit | B7: 18224 | C7: 22946 | D7: 28446 | E7: 43815 | F7: 43612
A8: Gross Profit Margin | B8: 0.34 | C8: 0.42 | D8: 0.45 | E8: 0.55 | F8: 0.56
A9: Total Operating Expenses | B9: 22053 | C9: 21680 | D9: 24530 | E9: 21733 | F9: 19736
A10: Operating Profit | B10: -3829 | C10: 1266 | D10: 3916 | E10: 22082 | F10: 23876
A11: Operating Margin | B11: -0.07 | C11: 0.02 | D11: 0.06 | E11: 0.28 | F11: 0.31
A12: Other Income | B12: -1100 | C12: 306 | D12: 420 | E12: 263 | F12: 214
A13: Interest expense | B13: -900 | C13: -700 | D13: -500 | E13: -400 | F13: -400
A14: Net Income | B14: -18756 | C14: 1689 | D14: 8014 | E14: 19868 | F14: 20899
A15: Comprehensive Income | B15: -18900 | C15: 1700 | D15: 8100 | E15: 19950 | F15: 21000
A16: Net Profit Margin | B16: -0.35 | C16: 0.03 | D16: 0.13 | E16: 0.25 | F16: 0.27
A18: Items (In $ Millions) | B18: 2024 | C18: 2023 | D18: 2022 | E18: 2021 | F18: 2020 | G18: 2019
A19: Total Revenue (In US millions) | B19: 53101 | C19: 54228 | D19: 63054 | E19: 79024 | F19: 77867 | G19: 71965
A20: Total Cost of Sales | B20: 34877 | C20: 31282 | D20: 34608 | E20: 35209 | F20: 34255 | G20: 30186
A22: Year-on-Year Change % | B22: 2024/23 | C22: 2023/22 | D22: 2022/21 | E22: 2021/20 | F22: 2020/19
A23: Total Revenues (Sales) | B23: =B19/C19-1 -> -0.020782622 | C23: =C19/D19-1 -> -0.13997526 | D23: =D19/E19-1 -> -0.2020905 | E23: =E19/F19-1 -> 0.014858669 | F23: =F19/G19-1 -> 0.082012089
A24: Total Cost of Sales | B24: =B20/C20-1 -> 0.11492232 | C24: =C20/D20-1 -> -0.096104947 | D24: =D20/E20-1 -> -0.017069499 | E24: =E20/F20-1 -> 0.027849949 | F24: =F20/G20-1 -> 0.13479759
A25: Total Operating Expenses | B25: =B9/C9-1 -> 0.017204797 | C25: =C9/D9-1 -> -0.11618426 | D25: =D9/E9-1 -> 0.12869829 | E25: =E9/F9-1 -> 0.10118565 | F25: =F9/2237-1 -> 7.8225302
A26: Gross Profit | B26: =B7/C7-1 -> -0.2057875 | C26: =C7/D7-1 -> -0.1933488 | D26: =D7/E7-1 -> -0.35077028 | E26: =E7/F7-1 -> 0.0046546822 | F26: =F7/2868-1 -> 14.206416
A27: Operating Profit (Loss) | B27: =B10/C10-1 -> -4.0244866 | C27: =C10/D10-1 -> -0.67671093 | D27: =D10/E10-1 -> -0.82266099 | E27: =E10/F10-1 -> -0.075138214 | F27: =F10/631-1 -> 36.838352
A28: Net Income | B28: =B14/C14-1 -> -12.104796 | C28: =C14/D14-1 -> -0.78924382 | D28: =D14/E14-1 -> -0.59663781 | E28: =E14/F14-1 -> -0.049332504 | F28: =F14/341-1 -> 60.28739
A30: Operating Expenses
A31: Items (In $ Millions) | B31: 2024 | C31: 2023 | D31: 2022 | E31: 2021 | F31: 2020
A32: Research and development | B32: 16546 | C32: 16046 | D32: 17528 | E32: 15190 | F32: 13556
A33: Marketing, general and administrative | B33: 5507 | C33: 5634 | D33: 7002 | E33: 6543 | F33: 6180
A34: Amortization of acquisition-related intangibles | B34: 300 | C34: 350 | D34: 400 | E34: - | F34: -
A35: Restructuring charges | B35: 100 | C35: -50 | D35: 150 | E35: 20 | F35: -
A36: Licensing gain | B36: - | C36: - | D36: 100 | E36: - | F36: -
A38: Investing Activities (CapEx)
A39: Items (In $ Millions) | B39: 2024 | C39: 2023 | D39: 2022 | E39: 2021 | F39: 2020
A40: Purchases of property and equipment | B40: -23944 | C40: -25750 | D40: -25050 | E40: -20329 | F40: -14260
A41: Purchases and proceeds related to short-term investments | B41: -1700 | C41: -1500 | D41: -1800 | E41: -1200 | F41: -800
A42: Acquisitions, net of cash acquired | B42: -1500 | C42: -400 | D42: -1700 | E42: -900 | F42: -300
A43: Proceeds from divestitures / IPO / asset sales | B43: 861 | C43: -353 | D43: 7000 | E43: - | F43: -
A44: Other | B44: -500 | C44: -100 | D44: -200 | E44: -150 | F44: -100
A46: Free Cash Flow
A47: Items (In $ Millions) | B47: 2024 | C47: 2023 | D47: 2022 | E47: 2021 | F47: 2020
A48: Cash from Operating Activities (CFO) | B48: 8288 | C48: 11471 | D48: 15433 | E48: 30033 | F48: 35391
A49: Cash used in Investing Activities (CapEx/CFInv) | B49: -18256 | C49: -24041 | D49: -10231 | E49: -18715 | F49: -14532
A50: Cash used in Financing Activities | B50: 11138 | C50: 8505 | D50: 1115 | E50: -4390 | F50: -2841
A51: Free Cash Flow (FCF) | B51: -9968 | C51: -12570 | D51: 5202 | E51: 11318 | F51: 20859
A53: SEGMENTATION DATA
A54: Segment | B54: 2024 | C54: 2023 | D54: 2022 | E54: 2021 | F54: 2020
A55: Data Center & AI (DCAI) | B55: 12817 | C55: 15521 | D55: 19445 | E55: 22774 | F55: 23413
A56: Client Computing (CCG) | B56: 30290 | C56: 29258 | D56: 31773 | E56: 41081 | F56: 40535
A57: Network & Edge (NEX) | B57: 5842 | C57: 5774 | D57: 8409 | E57: 7665 | F57: 7132
A58: Intel Foundry Services (IFS) | B58: 328 | C58: 952 | D58: 1869 | E58: 347 | F58: 715
A59: All other | B59: 3824 | C59: 2723 | D59: 1558 | E59: 7157 | F59: 6709
A60: Total Intel (Consolidated) | B60: =SUM(B55:B59) -> 53101 | C60: =SUM(C55:C59) -> 54228 | D60: =SUM(D55:D59) -> 63054 | E60: =SUM(E55:E59) -> 79024 | F60: =SUM(F55:F59) -> 78504
A62: GEOGRAPHICAL DATA
B63: 2024 | C63: 2023 | D63: 2022 | E63: 2021 | F63: 2020
A64: China (incl. Hong Kong) | B64: 15532 | C64: 14854 | D64: 17125 | E64: 21141 | F64: 20257
A65: United States | B65: 12994 | C65: 13958 | D65: 16529 | E65: 14107 | F65: 16573
A66: Singapore | B66: 10187 | C66: 8602 | D66: 9664 | E66: 14254 | F66: 17845
A67: Taiwan | B67: 7804 | C67: 6867 | D67: 8287 | E67: 13461 | F67: 11605
A68: Other regions / countries | B68: 6584 | C68: 9947 | D68: 11449 | E68: 16061 | F68: 11587
A69: Total Net Revenue | B69: 53101 | C69: 54228 | D69: 63054 | E69: 79024 | F69: 77867
